{
  "method": "GET",
  "url": "https://cdn.cookielaw.org/consent/04f73bfc-c643-4620-9c4b-fb8d44e993a5/04f73bfc-c643-4620-9c4b-fb8d44e993a5.json",
  "timestamp": "20250918_181756",
  "query": "",
  "headers": {
    "Host": "cdn.cookielaw.org",
    "User-Agent": "Mozilla/5.0 (Windows NT 10.0; Win64; x64; rv:143.0) Gecko/20100101 Firefox/143.0",
    "Accept": "*/*",
    "Accept-Language": "en-US,en;q=0.5",
    "Origin": "https://1v1.lol",
    "Connection": "keep-alive",
    "Referer": "https://1v1.lol/",
    "Sec-Fetch-Dest": "empty",
    "Sec-Fetch-Mode": "cors",
    "Sec-Fetch-Site": "cross-site",
    "Pragma": "no-cache",
    "Cache-Control": "no-cache",
    "Accept-Encoding": "gzip, deflate"
  },
  "response_status": 200,
  "response_headers": {
    "Date": "Thu, 18 Sep 2025 18:17:56 GMT",
    "Connection": "keep-alive",
    "Server": "cloudflare",
    "CF-Ray": "9812d7cf19dabd9f-LHR",
    "CF-Cache-Status": "HIT",
    "Access-Control-Allow-Origin": "*",
    "Age": "63860",
    "Cache-Control": "public, max-age=86400",
    "Strict-Transport-Security": "max-age=31536000; includeSubDomains; preload",
    "Vary": "Accept-Encoding",
    "Access-Control-Expose-Headers": "x-ms-request-id,Server,x-ms-version,Content-Type,Content-Encoding,Cache-Control,ETag,Last-Modified,Content-MD5,x-ms-lease-status,x-ms-blob-type,Content-Length,Date,Transfer-Encoding, X-OneTrust-IsBot",
    "Cross-Origin-Resource-Policy": "cross-origin, cross-origin",
    "X-Content-Type-Options": "nosniff",
    "x-ms-blob-type": "BlockBlob",
    "x-ms-lease-status": "unlocked",
    "x-ms-request-id": "f7327148-201e-0039-133a-23d32e000000",
    "x-ms-version": "2009-09-19",
    "X-OneTrust-IsBot": "true",
    "Transfer-Encoding": "chunked"
  },
  "response_filename": "04f73bfc-c643-4620-9c4b-fb8d44e993a5.json"
}